README.txt
httrack.py
setup.py
httrack_py.egg-info/PKG-INFO
httrack_py.egg-info/SOURCES.txt
httrack_py.egg-info/top_level.txt
src/httrack-py.c
test/test_extension.py
