Metadata-Version: 1.0
Name: httrack-py
Version: 0.6.1
Summary: httrack-py library: wrapper to use httrack website copier
Home-page: http://code.google.com/p/httrack-py
Author: Abel Deuring
Author-email: adeuring@gmx.net
License: http://www.fsf.org/licensing/licenses/lgpl.txt
Platform: unix
Platform: win32
Classifier: Development Status :: 3 - Alpha
Classifier: Intended Audience :: Developers
Classifier: License :: OSI Approved :: GNU Library or Lesser General Public License (LGPL)
Classifier: Programming Language :: Python
Classifier: Topic :: Software Development :: Libraries :: Python Modules
Classifier: Topic :: Software Development :: Libraries
Classifier: Topic :: Communications :: Email
Classifier: Operating System :: Unix
Classifier: Operating System :: POSIX
